Dragline-2.4.3.data/data/dragline/templates/main.tem
Dragline-2.4.3.data/data/dragline/templates/settings.tem
Dragline-2.4.3.data/scripts/dragline
Dragline-2.4.3.data/scripts/dragline-shell
Dragline-2.4.3.dist-info/DESCRIPTION.rst
Dragline-2.4.3.dist-info/METADATA
Dragline-2.4.3.dist-info/RECORD
Dragline-2.4.3.dist-info/WHEEL
Dragline-2.4.3.dist-info/metadata.json
Dragline-2.4.3.dist-info/top_level.txt
dragline/VERSION
dragline/__init__.py
dragline/crawl.py
dragline/item.py
dragline/redisds.py
dragline/runner.py
dragline/runtime.py
dragline/shell.py
dragline/utils.py
dragline/http/__init__.py
dragline/http/requests.py
dragline/http/selenium.py
dragline/http/webengine.py
dragline/parser/__init__.py
dragline/parser/funcs.py
dragline/parser/html.py
dragline/settings/__init__.py
dragline/settings/global_settings.py
dragline/templates/main.tem
dragline/templates/settings.tem
