Metadata-Version: 2.0
Name: Dragline
Version: 2.4.3
Summary: Distributed Python web crawling framework
Home-page: http://www.inzyte.com
Author: Ashwin Rajeev, Shimil Rahman
Author-email: ashwin@inzyte.com, shimil@inzyte.com
License: UNKNOWN
Platform: UNKNOWN
Classifier: Programming Language :: Python
Classifier: Programming Language :: Python :: 2.7
Classifier: License :: OSI Approved :: BSD License
Classifier: Operating System :: POSIX :: Linux
Classifier: Development Status :: 5 - Production/Stable
Classifier: Intended Audience :: Developers
Classifier: Environment :: Console
Classifier: Topic :: Software Development :: Libraries :: Application Frameworks
Classifier: Topic :: Software Development :: Libraries :: Python Modules
Classifier: Topic :: Internet :: WWW/HTTP
Requires-Dist: cssselect
Requires-Dist: gevent (==1.2.0)
Requires-Dist: lxml
Requires-Dist: pytz
Requires-Dist: redis (==2.10.0)
Requires-Dist: requests (==2.5.1)
Requires-Dist: six
